charmonium/cache/__init__.py
charmonium/cache/helpers.py
charmonium/cache/index.py
charmonium/cache/memoize.py
charmonium/cache/obj_store.py
charmonium/cache/pathlike.py
charmonium/cache/pickler.py
charmonium/cache/py.typed
charmonium/cache/replacement_policies.py
charmonium/cache/rw_lock.py
charmonium/cache/util.py
charmonium_cache-1.4.1.dist-info/LICENSE
charmonium_cache-1.4.1.dist-info/METADATA
charmonium_cache-1.4.1.dist-info/WHEEL
charmonium_cache-1.4.1.dist-info/entry_points.txt
charmonium_cache-1.4.1.dist-info/RECORD
