Metadata-Version: 2.1
Name: charmonium-cache
Version: 1.4.1
Summary: Provides a decorator for caching a function between subsequent processes.
Home-page: https://github.com/charmoniumQ/charmonium.cache
License: MIT
Keywords: cache,memoize,decorator
Author: Samuel Grayson
Author-email: sam+dev@samgrayson.me
Requires-Python: >=3.8,<4.0
Classifier: Development Status :: 5 - Production/Stable
Classifier: Intended Audience :: Developers
Classifier: Intended Audience :: Science/Research
Classifier: License :: OSI Approved :: MIT License
Classifier: Natural Language :: English
Classifier: Operating System :: OS Independent
Classifier: Programming Language :: Python :: 3
Classifier: Programming Language :: Python :: 3.8
Classifier: Programming Language :: Python :: 3.9
Classifier: Programming Language :: Python :: 3.10
Classifier: Programming Language :: Python :: 3.11
Classifier: Topic :: Scientific/Engineering
Classifier: Topic :: Software Development :: Libraries :: Python Modules
Classifier: Typing :: Typed
Requires-Dist: bitmath (>=1.3,<2.0)
Requires-Dist: charmonium.freeze (>=0.8.1,<2)
Requires-Dist: fasteners (>=0.16,<2)
Project-URL: Documentation, https://charmoniumq.github.io/charmonium.cache/
Project-URL: Repository, https://github.com/charmoniumQ/charmonium.cache
